coop_kobe_parser/__init__.py
coop_kobe_parser/__main__.py
coop_kobe_parser/logger.py
coop_kobe_parser/parsers/__init__.py
coop_kobe_parser/parsers/product.py
coop_kobe_parser/parsers/summary.py
coop_kobe_parser-0.1.2.dist-info/METADATA
coop_kobe_parser-0.1.2.dist-info/WHEEL
coop_kobe_parser-0.1.2.dist-info/entry_points.txt
coop_kobe_parser-0.1.2.dist-info/licenses/LICENSE
coop_kobe_parser-0.1.2.dist-info/RECORD
