Metadata-Version: 2.3
Name: coop-kobe-parser
Version: 0.1.2
Summary: コープこうべの宅配の注文書(CSV)をパースするPythonパッケージ
Project-URL: Homepage, https://github.com/ryohidaka/coop-kobe-parser
Project-URL: Repository, https://github.com/ryohidaka/coop-kobe-parser
Project-URL: Issues, https://github.com/ryohidaka/coop-kobe-parser/issues
Project-URL: Changelog, https://github.com/ryohidaka/blob/main/coop-kobe-parser/CHANGELOG.md
Author-email: ryohidaka <39184410+ryohidaka@users.noreply.github.com>
License: MIT License
License-File: LICENSE
Keywords: coop,csv,japan,japanese,parser
Requires-Python: >=3.8
Requires-Dist: pandas>=2.2.2
